ip2geotools_locator/__init__.py
ip2geotools_locator/cli.py
ip2geotools_locator/folium_map.py
ip2geotools_locator/main.py
ip2geotools_locator/utils.py
ip2geotools_locator/calculations/__init__.py
ip2geotools_locator/calculations/average.py
ip2geotools_locator/calculations/clustering.py
ip2geotools_locator/calculations/median.py
ip2geotools_locator/database_connectors/__init__.py
ip2geotools_locator/database_connectors/eurek.py
ip2geotools_locator/database_connectors/geobytes_city.py
ip2geotools_locator/database_connectors/host_ip.py
ip2geotools_locator/database_connectors/ip2location.py
ip2geotools_locator/database_connectors/ip2location_web.py
ip2geotools_locator/database_connectors/ip_city.py
ip2geotools_locator/database_connectors/ip_info.py
ip2geotools_locator/database_connectors/ip_web.py
ip2geotools_locator/database_connectors/ipstack.py
ip2geotools_locator/database_connectors/max_mind.py
ip2geotools_locator/database_connectors/max_mind_lite.py
ip2geotools_locator/database_connectors/neustar_web.py
ip2geotools_locator/database_connectors/skyhook.py
ip2geotools_locator-1.6.0.dist-info/LICENSE
ip2geotools_locator-1.6.0.dist-info/METADATA
ip2geotools_locator-1.6.0.dist-info/WHEEL
ip2geotools_locator-1.6.0.dist-info/entry_points.txt
ip2geotools_locator-1.6.0.dist-info/top_level.txt
ip2geotools_locator-1.6.0.dist-info/RECORD
