Metadata-Version: 2.1
Name: ip2geotools-locator
Version: 1.6.0
Summary: An extension of the ip2geotools package that refines
Home-page: https://github.com/Ionicson/ip2geotools-locator
Author: Oldřich Klíma
Author-email: xklima27@vutbr.cz
License: MIT license
Keywords: ip2geotools-locator
Platform: UNKNOWN
Classifier: Development Status :: 5 - Production/Stable
Classifier: Intended Audience :: Developers
Classifier: License :: OSI Approved :: MIT License
Classifier: Natural Language :: English
Classifier: Programming Language :: Python :: 3
Classifier: Programming Language :: Python :: 3.4
Classifier: Programming Language :: Python :: 3.5
Classifier: Programming Language :: Python :: 3.6
Classifier: Programming Language :: Python :: 3.7
Requires-Dist: Click (>=6.0)
Requires-Dist: folium (>=0.6.0)
Requires-Dist: geopy (>=1.17.0)
Requires-Dist: ip2geotools (>=0.1.4)
Requires-Dist: kneed (>=0.2.4)
Requires-Dist: scipy (>=1.1.0)
Requires-Dist: sklearn (>=0.0)
